{"trial_id": "00", "hyperparameters": {"space": [{"class_name": "Int", "config": {"name": "units_l1", "default": null, "conditions": [], "min_value": 32, "max_value": 512, "step": 32, "sampling": "linear"}}, {"class_name": "Choice", "config": {"name": "activation_l1", "default": "elu", "conditions": [], "values": ["elu", "gelu", "relu", "tanh", "leaky_relu", "mish", "silu", "celu"], "ordered": false}}, {"class_name": "Float", "config": {"name": "dropout_l1", "default": 0.0, "conditions": [], "min_value": 0.0, "max_value": 0.5, "step": 0.1, "sampling": "linear"}}, {"class_name": "Int", "config": {"name": "units_l2", "default": null, "conditions": [], "min_value": 32, "max_value": 512, "step": 32, "sampling": "linear"}}, {"class_name": "Choice", "config": {"name": "activation_l2", "default": "elu", "conditions": [], "values": ["elu", "gelu", "relu", "tanh", "leaky_relu", "mish", "silu", "celu"], "ordered": false}}, {"class_name": "Float", "config": {"name": "dropout_l2", "default": 0.0, "conditions": [], "min_value": 0.0, "max_value": 0.5, "step": 0.1, "sampling": "linear"}}, {"class_name": "Boolean", "config": {"name": "add_l3", "default": false, "conditions": []}}, {"class_name": "Boolean", "config": {"name": "add_l4", "default": false, "conditions": []}}, {"class_name": "Boolean", "config": {"name": "add_l5", "default": false, "conditions": []}}, {"class_name": "Boolean", "config": {"name": "add_l6", "default": false, "conditions": []}}, {"class_name": "Float", "config": {"name": "lr", "default": 0.0001, "conditions": [], "min_value": 0.0001, "max_value": 0.01, "step": null, "sampling": "log"}}, {"class_name": "Choice", "config": {"name": "optimizer", "default": "SGD", "conditions": [], "values": ["SGD", "RMSprop", "Adam"], "ordered": false}}, {"class_name": "Choice", "config": {"name": "loss", "default": "mse", "conditions": [], "values": ["mse", "mae", "huber"], "ordered": false}}, {"class_name": "Int", "config": {"name": "units_l4", "default": null, "conditions": [], "min_value": 32, "max_value": 512, "step": 32, "sampling": "linear"}}, {"class_name": "Choice", "config": {"name": "activation_l4", "default": "elu", "conditions": [], "values": ["elu", "gelu", "relu", "tanh", "leaky_relu", "mish", "silu", "celu"], "ordered": false}}, {"class_name": "Float", "config": {"name": "dropout_l4", "default": 0.0, "conditions": [], "min_value": 0.0, "max_value": 0.5, "step": 0.1, "sampling": "linear"}}, {"class_name": "Int", "config": {"name": "units_l5", "default": null, "conditions": [], "min_value": 32, "max_value": 512, "step": 32, "sampling": "linear"}}, {"class_name": "Choice", "config": {"name": "activation_l5", "default": "elu", "conditions": [], "values": ["elu", "gelu", "relu", "tanh", "leaky_relu", "mish", "silu", "celu"], "ordered": false}}, {"class_name": "Float", "config": {"name": "dropout_l5", "default": 0.0, "conditions": [], "min_value": 0.0, "max_value": 0.5, "step": 0.1, "sampling": "linear"}}, {"class_name": "Int", "config": {"name": "units_l6", "default": null, "conditions": [], "min_value": 32, "max_value": 512, "step": 32, "sampling": "linear"}}, {"class_name": "Choice", "config": {"name": "activation_l6", "default": "elu", "conditions": [], "values": ["elu", "gelu", "relu", "tanh", "leaky_relu", "mish", "silu", "celu"], "ordered": false}}, {"class_name": "Float", "config": {"name": "dropout_l6", "default": 0.0, "conditions": [], "min_value": 0.0, "max_value": 0.5, "step": 0.1, "sampling": "linear"}}], "values": {"units_l1": 512, "activation_l1": "relu", "dropout_l1": 0.2, "units_l2": 96, "activation_l2": "mish", "dropout_l2": 0.4, "add_l3": false, "add_l4": true, "add_l5": true, "add_l6": true, "lr": 0.0005674460859990781, "optimizer": "Adam", "loss": "mae", "units_l4": 32, "activation_l4": "elu", "dropout_l4": 0.0, "units_l5": 32, "activation_l5": "elu", "dropout_l5": 0.0, "units_l6": 32, "activation_l6": "elu", "dropout_l6": 0.0}}, "metrics": {"metrics": {}}, "score": null, "best_step": 0, "status": "FAILED", "message": "Traceback (most recent call last):\n  File \"c:\\Users\\lkimd\\anaconda3\\envs\\cse150b\\Lib\\site-packages\\keras_tuner\\src\\engine\\base_tuner.py\", line 274, in _try_run_and_update_trial\n    self._run_and_update_trial(trial, *fit_args, **fit_kwargs)\n  File \"c:\\Users\\lkimd\\anaconda3\\envs\\cse150b\\Lib\\site-packages\\keras_tuner\\src\\engine\\base_tuner.py\", line 239, in _run_and_update_trial\n    results = self.run_trial(trial, *fit_args, **fit_kwargs)\n              ^^^^^^^^^^^^^^^^^^^^^^^^^^^^^^^^^^^^^^^^^^^^^^\n  File \"c:\\Users\\lkimd\\anaconda3\\envs\\cse150b\\Lib\\site-packages\\keras_tuner\\src\\engine\\tuner.py\", line 314, in run_trial\n    obj_value = self._build_and_fit_model(trial, *args, **copied_kwargs)\n                ^^^^^^^^^^^^^^^^^^^^^^^^^^^^^^^^^^^^^^^^^^^^^^^^^^^^^^^^\n  File \"c:\\Users\\lkimd\\anaconda3\\envs\\cse150b\\Lib\\site-packages\\keras_tuner\\src\\engine\\tuner.py\", line 233, in _build_and_fit_model\n    results = self.hypermodel.fit(hp, model, *args, **kwargs)\n              ^^^^^^^^^^^^^^^^^^^^^^^^^^^^^^^^^^^^^^^^^^^^^^^\n  File \"c:\\Users\\lkimd\\anaconda3\\envs\\cse150b\\Lib\\site-packages\\keras_tuner\\src\\engine\\hypermodel.py\", line 149, in fit\n    return model.fit(*args, **kwargs)\n           ^^^^^^^^^^^^^^^^^^^^^^^^^^\n  File \"c:\\Users\\lkimd\\anaconda3\\envs\\cse150b\\Lib\\site-packages\\keras\\src\\utils\\traceback_utils.py\", line 122, in error_handler\n    raise e.with_traceback(filtered_tb) from None\n  File \"c:\\Users\\lkimd\\anaconda3\\envs\\cse150b\\Lib\\site-packages\\optree\\ops.py\", line 766, in tree_map\n    return treespec.unflatten(map(func, *flat_args))\n           ^^^^^^^^^^^^^^^^^^^^^^^^^^^^^^^^^^^^^^^^^\nValueError: Invalid dtype: object\n"}